{
  "rentals": [
    {
      "title": "Big condo in center",
      "city": "Timisoara",
      "street": "Piata Craiului",
      "category": "condo",
      "image": "https://booksync-jerga-prod.s3.amazonaws.com/uploads/rental/image/1/image.jpeg",
      "bedrooms": 3,
      "shared": false,
      "description": "Very nice apartment in center of the city.",
      "dailyRate": 43
    },
    {
      "title": "Modern apartment in center",
      "city": "Timisoara",
      "street": "Paris",
      "category": "apartment",
      "image": "https://booksync-jerga-prod.s3.amazonaws.com/uploads/rental/image/2/image.jpeg",
      "bedrooms": 1,
      "shared": true,
      "description": "Very nice Modern apartment in center of the city.",
      "dailyRate": 20
    },
    {
      "title": "Spy apartment",
      "city": "Arad",
      "street": "Adi Endre",
      "category": "apartment",
      "image": "https://booksync-jerga-prod.s3.amazonaws.com/uploads/rental/image/3/image.jpeg",
      "bedrooms": 2,
      "shared": false,
      "description": "Sky apartment in center of the city.",
      "dailyRate": 23
    },
    {
      "title": "House near Timisoara",
      "city": "Ghiroc",
      "street": "George",
      "category": "house",
      "image": "https://booksync-jerga-prod.s3.amazonaws.com/uploads/rental/image/5/image.jpeg",
      "bedrooms": 3,
      "shared": false,
      "description": "Hiking routes 10 min walking away",
      "dailyRate": 50
    },
    {
      "title": "Apartment Cluj",
      "city": "Cluj",
      "street": "Unirii",
      "category": "apartment",
      "image": "https://booksync-jerga-prod.s3.amazonaws.com/uploads/rental/image/4/image.jpeg",
      "bedrooms": 2,
      "shared": false,
      "description": "Very nice apartment in Cluj",
      "dailyRate": 39
    },
    {
      "title": "House with Garden",
      "city": "Remetea",
      "street": "Main Street",
      "category": "house",
      "image": "https://booksync-jerga-prod.s3.amazonaws.com/uploads/rental/image/6/image.jpeg",
      "bedrooms": 3,
      "shared": false,
      "description": "Very nice house in Remetea with garden",
      "dailyRate": 60
    },
    {
      "title": "Cozy modern Condo",
      "city": "Dumbravita",
      "street": "Ghioceilor",
      "category": "condo",
      "image": "https://booksync-jerga-prod.s3.amazonaws.com/uploads/rental/image/7/image.jpeg",
      "bedrooms": 4,
      "shared": true,
      "description": "Building close Timisoara",
      "dailyRate": 68
    },
    {
      "title": "Condo near river",
      "city": "Oradea",
      "street": "Brancus",
      "category": "condo",
      "image": "https://booksync-jerga-prod.s3.amazonaws.com/uploads/rental/image/8/image.jpeg",
      "bedrooms": 2,
      "shared": true,
      "description": "Building close to river",
      "dailyRate": 48
    }
  ],
  "users": [
    {
      "username": "Alex",
      "email": "test@gmail.com",
      "password": "testtest"
    },
    {
      "username": "Andrei",
      "email": "test1@gmail.com",
      "password": "testtest1"
    }
  ]
}
